button_beaver/__main__.py
button_beaver/adder.py
button_beaver/model.py
button_beaver/urls.py
button_beaver/version.py
button_beaver-0.2.0.dev0.dist-info/METADATA
button_beaver-0.2.0.dev0.dist-info/WHEEL
button_beaver-0.2.0.dev0.dist-info/licenses/LICENSE
button_beaver-0.2.0.dev0.dist-info/RECORD
